[
  {
    "ContainingType": "CitizenConnect.Controllers.AdminController",
    "Method": "GetComplaintHistory",
    "RelativePath": "api/Admin/complaint-history/{complaintId}",
    "HttpMethod": "GET",
    "IsController": true,
    "Order": 0,
    "Parameters": [
      {
        "Name": "complaintId",
        "Type": "System.Int32",
        "IsRequired": true
      }
    ],
    "ReturnTypes": []
  },
  {
    "ContainingType": "CitizenConnect.Controllers.AdminController",
    "Method": "GetAllComplaints",
    "RelativePath": "api/Admin/complaints",
    "HttpMethod": "GET",
    "IsController": true,
    "Order": 0,
    "Parameters": [],
    "ReturnTypes": []
  },
  {
    "ContainingType": "CitizenConnect.Controllers.AdminController",
    "Method": "UpdateComplaintStatus",
    "RelativePath": "api/Admin/update-status",
    "HttpMethod": "PUT",
    "IsController": true,
    "Order": 0,
    "Parameters": [
      {
        "Name": "dto",
        "Type": "CitizenConnect.DTOs.Admin.UpdateComplaintStatusDto",
        "IsRequired": true
      }
    ],
    "ReturnTypes": []
  },
  {
    "ContainingType": "CitizenConnect.API.Controllers.AuthController",
    "Method": "Login",
    "RelativePath": "api/auth/login",
    "HttpMethod": "POST",
    "IsController": true,
    "Order": 0,
    "Parameters": [
      {
        "Name": "dto",
        "Type": "CitizenConnect.Application.DTOs.Auth.LoginRequestDto",
        "IsRequired": true
      }
    ],
    "ReturnTypes": []
  },
  {
    "ContainingType": "CitizenConnect.API.Controllers.AuthController",
    "Method": "RegisterCitizen",
    "RelativePath": "api/auth/register-citizen",
    "HttpMethod": "POST",
    "IsController": true,
    "Order": 0,
    "Parameters": [
      {
        "Name": "dto",
        "Type": "CitizenConnect.Application.DTOs.Auth.RegisterCitizenDto",
        "IsRequired": true
      }
    ],
    "ReturnTypes": []
  },
  {
    "ContainingType": "CitizenConnect.API.Controllers.AuthController",
    "Method": "RegisterPolitician",
    "RelativePath": "api/auth/register-politician",
    "HttpMethod": "POST",
    "IsController": true,
    "Order": 0,
    "Parameters": [
      {
        "Name": "dto",
        "Type": "CitizenConnect.Application.DTOs.Auth.RegisterPoliticianDto",
        "IsRequired": true
      }
    ],
    "ReturnTypes": []
  },
  {
    "ContainingType": "CitizenConnect.Controllers.ComplaintController",
    "Method": "GetComplaintDetails",
    "RelativePath": "api/Complaint/{complaintId}",
    "HttpMethod": "GET",
    "IsController": true,
    "Order": 0,
    "Parameters": [
      {
        "Name": "complaintId",
        "Type": "System.Int32",
        "IsRequired": true
      }
    ],
    "ReturnTypes": []
  },
  {
    "ContainingType": "CitizenConnect.Controllers.ComplaintController",
    "Method": "GetComplaintCategories",
    "RelativePath": "api/Complaint/categories",
    "HttpMethod": "GET",
    "IsController": true,
    "Order": 0,
    "Parameters": [],
    "ReturnTypes": []
  },
  {
    "ContainingType": "CitizenConnect.Controllers.ComplaintController",
    "Method": "GetCitizenComplaints",
    "RelativePath": "api/Complaint/citizen/{citizenId}",
    "HttpMethod": "GET",
    "IsController": true,
    "Order": 0,
    "Parameters": [
      {
        "Name": "citizenId",
        "Type": "System.Int32",
        "IsRequired": true
      }
    ],
    "ReturnTypes": []
  },
  {
    "ContainingType": "CitizenConnect.Controllers.ComplaintController",
    "Method": "CreateComplaint",
    "RelativePath": "api/Complaint/create",
    "HttpMethod": "POST",
    "IsController": true,
    "Order": 0,
    "Parameters": [
      {
        "Name": "CitizenId",
        "Type": "System.Int32",
        "IsRequired": false
      },
      {
        "Name": "WardId",
        "Type": "System.Int32",
        "IsRequired": false
      },
      {
        "Name": "ComplaintCategoryId",
        "Type": "System.Int32",
        "IsRequired": false
      },
      {
        "Name": "Title",
        "Type": "System.String",
        "IsRequired": false
      },
      {
        "Name": "Description",
        "Type": "System.String",
        "IsRequired": false
      },
      {
        "Name": "Address",
        "Type": "System.String",
        "IsRequired": false
      },
      {
        "Name": "Latitude",
        "Type": "System.Decimal",
        "IsRequired": false
      },
      {
        "Name": "Longitude",
        "Type": "System.Decimal",
        "IsRequired": false
      },
      {
        "Name": "Priority",
        "Type": "System.String",
        "IsRequired": false
      },
      {
        "Name": "IsAnonymous",
        "Type": "System.Boolean",
        "IsRequired": false
      },
      {
        "Name": "Files",
        "Type": "System.Collections.Generic.List\u00601[[Microsoft.AspNetCore.Http.IFormFile, Microsoft.AspNetCore.Http.Features, Version=8.0.0.0, Culture=neutral, PublicKeyToken=adb9793829ddae60]]",
        "IsRequired": false
      }
    ],
    "ReturnTypes": []
  },
  {
    "ContainingType": "CitizenConnect.API.Controllers.MasterController",
    "Method": "GetJurisdictionTypes",
    "RelativePath": "api/master/jurisdiction-types",
    "HttpMethod": "GET",
    "IsController": true,
    "Order": 0,
    "Parameters": [],
    "ReturnTypes": []
  },
  {
    "ContainingType": "CitizenConnect.API.Controllers.MasterController",
    "Method": "GetResidenceTypes",
    "RelativePath": "api/master/residence-types",
    "HttpMethod": "GET",
    "IsController": true,
    "Order": 0,
    "Parameters": [],
    "ReturnTypes": []
  },
  {
    "ContainingType": "CitizenConnect.API.Controllers.MasterController",
    "Method": "GetWards",
    "RelativePath": "api/master/wards",
    "HttpMethod": "GET",
    "IsController": true,
    "Order": 0,
    "Parameters": [],
    "ReturnTypes": []
  }
]